{
    "1": {
        "audio": "en_garde_espece_de_vieille_pute_degarnie.mp3",
        "text": "En garde, espèce de vieille pute dégarnie !"
    },
    "2": {
        "audio": "je_ne_mange_pas_de_graines.mp3",
        "text": "JE NE MANGE PAS DE GRAINES !"
    },
    "3": {
        "audio": "alors_ca_vient_ptite_bite.mp3",
        "text": "Alors ça vient? p'tite bite !"
    },
    "4": {
        "audio": "ma_femme_a_pas_de_moustache.mp3",
        "text": "Mais moi, ma femme n'a pas de moustache !"
    },
    "5": {
        "audio": "sire_petite_pedale_pisse_froc.mp3",
        "text": "HAHA, Sire ! Je vous attends ! À moins que vous préfériez que l’on dise partout que le roi est une petite pédale qui pisse dans son froc à l’idée de se battre !"
    },
    "6": {
        "audio": "en_garde_grosse_conne.mp3",
        "text": "ALLEZ, EN GARDE GROSSE CONNE !"
    },
    "7": {
        "audio": "magnez_vous_fion_espece_de_grosse_dinde.mp3",
        "text": "Mais allez-y bon sang, magnez-vous le fion, espèce de grosse dinde !"
    },
    "8": {
        "audio": "comportement_peteux.mp3",
        "text": "Je commence à en avoir ras le bol de votre comportement de péteux "
    },
    "9": {
        "audio": "bande_de_trous_du_cul.mp3",
        "text": "BANDE DE TROUS DU CUL !!!"
    },
    "10": {
        "audio": "nerf_lapinou_zizi_pointe.mp3",
        "text": "Du nerf, mon lapinou !… Vous allez vous faire tailler le zizi en pointe !"
    },
    "11": {
        "audio": "coincer_parties_porte.mp3",
        "text": "Non mais c'est à se coincer les parties dans une porte !"
    },
    "12": {
        "audio": "ptite_pucelle.mp3",
        "text": "P'tite Pucelle"
    },
    "13": {
        "audio": "vous_etes_completement_con.mp3",
        "text": "MAIS VOUS ÊTES COMPLÈTEMENT CONS !"
    },
    "14": {
        "audio": "fils_d_unijambiste.mp3",
        "text": "Fils d'unijambiste"
    },
    "15": {
        "audio": "ptite_tapette.mp3",
        "text": "P'tite tapette, à la volette !"
    },
    "16": {
        "audio": "ferme_ta_gueule.mp3",
        "text": "Ferme ta gueule"
    },
    "17": {
        "audio": "soupcon_gros_nul.mp3",
        "text": "J'vous soupçonne d'être un gros nul"
    },
    "18": {
        "audio": "mais_je_vous_emmerde_mon_ptit_pote.mp3",
        "text": "Mais je vous emmerde mon p'tit pote"
    },
    "19": {
        "audio": "sortez-vous_les_doigts_du_cul.mp3",
        "text": "SORTEZ-VOUS LES DOIGTS DU CUL"
    },
    "20": {
        "audio": "un_jour_je_vais_lui_fumer_sa_gueule_a_ce_connard.mp3",
        "text": "Un jour j'vais lui fumer sa gueule à c'connard."
    },
    "21": {
        "audio": "vous_allez_fermer_vos_mouilles_oui.mp3",
        "text": "VOUS ALLEZ FERMER VOS MOUILLES OUI ?"
    },
    "22": {
        "audio": "venir_foutre_votre_merde.mp3",
        "text": "Faut toujours que vous veniez foutre votre merde"
    },
    "23": {
        "audio": "coup_de_beche.mp3",
        "text": "Coup de bèche dans la tête"
    },
    "24": {
        "audio": "restez_pas_plante_la_comme_un_cepe.mp3",
        "text": "Ne restez pas planté là comme un cèpe,"
    },
    "25": {
        "audio": "mecreant.mp3",
        "text": "MÉCRÉANT !"
    },
    "26": {
        "audio": "vous_etes_des_damnes.mp3",
        "text": "VOUS ÊTES DES DAMNÉS !"
    },
    "27": {
        "audio": "malademental.mp3",
        "text": "Vous êtes un grand malade mental !"
    },
    "28": {
        "audio": "parfaitement_antipathique.mp3",
        "text": "Et vous êtes parfaitement antipathique."
    },
    "29": {
        "audio": "mais_allez_chier_dans_une_fiolle.mp3",
        "text": "Mais allez chier dans une fiole, on verra après"
    },
    "30": {
        "audio": "mous_tige.mp3",
        "text": "Mou de la tige"
    },
    "31": {
        "audio": "fumiers.mp3",
        "text": "FUMIEEEERS !!!!"
    },
    "32": {
        "audio": "peau_de_vache.mp3",
        "text": "Peau de vache"
    },
    "33": {
        "audio": "glandeur_gros_glandeur.mp3",
        "text": "Z'êtes un glandeur. Un gros... GLANDEUR !!!"
    },
    "34": {
        "audio": "oh_le_con_pas_fini_affiner.mp3",
        "text": "Oh le con! Mais il est pas fini d'affiner!"
    },
    "35": {
        "audio": "crame_ta_famille.mp3",
        "text": "Toi, un jour, je te crâme ta famille, toi."
    },
    "36": {
        "audio": "gonfler_longtemps_rouquine.mp3",
        "text": "Ouh làlà! elle va pas me gonfler longtemps, la rouquine !!!"
    },
    "37": {
        "audio": "boite_a_caca.mp3",
        "text": "Alors le cageot il dit merci et il ferme sa boîte à caca !!!"
    }
}